README.md
setup.py
miniot_hts/__init__.py
miniot_hts/dht.py
miniot_hts/htsensor.py
miniot_hts.egg-info/PKG-INFO
miniot_hts.egg-info/SOURCES.txt
miniot_hts.egg-info/dependency_links.txt
miniot_hts.egg-info/not-zip-safe
miniot_hts.egg-info/top_level.txt