Metadata-Version: 1.1
Name: miniot-hts
Version: 0.8
Summary: A library to control Humid Temperature Sensor DHT11.
Home-page: https://github.com/shibats/miniot_hts/
Author: Atsushi Shibata
Author-email: shibata@m-info.co.jp
License: MIT
Platform: UNKNOWN
Classifier: Development Status :: 4 - Beta
Classifier: Operating System :: POSIX :: Linux
Classifier: Operating System :: MacOS :: MacOS X
Classifier: Operating System :: Microsoft :: Windows
Classifier: License :: OSI Approved :: MIT License
Classifier: Intended Audience :: Developers
Classifier: Programming Language :: Python :: 3
Classifier: Topic :: Software Development
Classifier: Topic :: System :: Hardware
